setup.py
src/zato/__init__.py
src/zato/invoke_retry/__init__.py
src/zato_invoke_retry.egg-info/PKG-INFO
src/zato_invoke_retry.egg-info/SOURCES.txt
src/zato_invoke_retry.egg-info/dependency_links.txt
src/zato_invoke_retry.egg-info/namespace_packages.txt
src/zato_invoke_retry.egg-info/not-zip-safe
src/zato_invoke_retry.egg-info/requires.txt
src/zato_invoke_retry.egg-info/top_level.txt