Metadata-Version: 1.1
Name: zato-invoke-retry
Version: 1.1.1
Summary: Zato 1.1 service providing invoke_retry & invoke_async_methods for retrying invocations, blockingly or in background (https://zato.io/docs/index.html)
Home-page: https://zato.io
Author: Zato Developers
Author-email: info@zato.io
License: GNU Lesser General Public License v3 (LGPLv3)
Keywords: soa eai esb middleware messaging queueing asynchronous integration performance http zeromq framework events agile broker messaging server jms enterprise python middleware clustering amqp nosql websphere mq wmq mqseries ibm amqp zmq
Platform: OS Independent
Classifier: Development Status :: 5 - Production/Stable
Classifier: Environment :: Console
Classifier: Framework :: Buildout
Classifier: Intended Audience :: Customer Service
Classifier: Intended Audience :: Developers
Classifier: Intended Audience :: Financial and Insurance Industry
Classifier: Intended Audience :: Healthcare Industry
Classifier: Intended Audience :: Information Technology
Classifier: Intended Audience :: Telecommunications Industry
Classifier: License :: OSI Approved :: GNU Lesser General Public License v3 (LGPLv3)
Classifier: Natural Language :: English
Classifier: Operating System :: OS Independent
Classifier: Programming Language :: C
Classifier: Programming Language :: Python :: 2 :: Only
Classifier: Programming Language :: Python :: 2.7
Classifier: Operating System :: POSIX :: Linux
Classifier: Operating System :: MacOS :: MacOS X
Classifier: Topic :: Communications
Classifier: Topic :: Database
Classifier: Topic :: Internet
Classifier: Topic :: Internet :: WWW/HTTP :: WSGI :: Server
Classifier: Topic :: Internet :: File Transfer Protocol (FTP)
Classifier: Topic :: Software Development :: Libraries :: Python Modules
Classifier: Topic :: Software Development :: Object Brokering
